todo_cli/alembic.ini
todo_cli/database.py
todo_cli/main.py
todo_cli/models.py
todo_cli/alembic/README
todo_cli/alembic/env.py
todo_cli/alembic/script.py.mako
todo_cli/alembic/versions/0abab7881256_.py
todo_cli/alembic/versions/22033ea27803_.py
todo_cli/cli/__init__.py
todo_cli/cli/main.py
todo_cli/ui/__init__.py
todo_cli/ui/main.py
rich_todo-0.1.6.dist-info/METADATA
rich_todo-0.1.6.dist-info/WHEEL
rich_todo-0.1.6.dist-info/entry_points.txt
rich_todo-0.1.6.dist-info/top_level.txt
rich_todo-0.1.6.dist-info/RECORD
