Metadata-Version: 2.2
Name: rich-todo
Version: 0.1.6
Summary: A CLI tool for managing todos directly from the terminal
Author: Mehran Mirzaei
Author-email: mehranmirzaeiv@gmail.com
Keywords: todo,cli,productivity
Classifier: Programming Language :: Python :: 3
Classifier: License :: OSI Approved :: MIT License
Classifier: Operating System :: OS Independent
Requires-Python: >=3.6
Requires-Dist: sqlalchemy
Requires-Dist: alembic
Requires-Dist: typer
Requires-Dist: rich
Requires-Dist: platformdirs
Requires-Dist: ttkbootstrap
Requires-Dist: customtkinter
Requires-Dist: tkcalendar
Dynamic: author
Dynamic: author-email
Dynamic: classifier
Dynamic: description
Dynamic: description-content-type
Dynamic: keywords
Dynamic: requires-dist
Dynamic: requires-python
Dynamic: summary
